testAppResponse/__init__.py
testAppResponse/asgi.py
testAppResponse/responses.py
testAppResponse/settings.py
testAppResponse/urls.py
testAppResponse/wsgi.py
testAppResponse-1.2.dist-info/METADATA
testAppResponse-1.2.dist-info/WHEEL
testAppResponse-1.2.dist-info/top_level.txt
testAppResponse-1.2.dist-info/RECORD
