Metadata-Version: 2.2
Name: testAppResponse
Version: 1.2
Summary: Manage your responses
Author: Manojan
Author-email: manojan.mano@gmail.com
Classifier: Programming Language :: Python :: 3
Classifier: License :: OSI Approved :: MIT License
Classifier: Operating System :: OS Independent
Requires-Python: >=3.6
Dynamic: author
Dynamic: author-email
Dynamic: classifier
Dynamic: requires-python
Dynamic: summary
